piday/__init__.py
piday/piday.py
cat_piday-0.1.1.dist-info/METADATA
cat_piday-0.1.1.dist-info/WHEEL
cat_piday-0.1.1.dist-info/entry_points.txt
cat_piday-0.1.1.dist-info/top_level.txt
cat_piday-0.1.1.dist-info/RECORD
